kuttychurn/__init__.py
kuttychurn/data_preparation.py
kuttychurn/feature_engineering.py
kuttychurn/model_training.py
kuttychurn/predict.py
kuttychurn/visualize.py
kuttychurn-0.1.0.dist-info/LICENSE
kuttychurn-0.1.0.dist-info/METADATA
kuttychurn-0.1.0.dist-info/WHEEL
kuttychurn-0.1.0.dist-info/RECORD
