Metadata-Version: 2.1
Name: kuttychurn
Version: 0.1.0
Summary: 
License: MIT
Author: kuttykishorekk
Author-email: kishorekumar.mourougane@epita.fr
Requires-Python: >=3.8,<4.0
Classifier: License :: OSI Approved :: MIT License
Classifier: Programming Language :: Python :: 3
Classifier: Programming Language :: Python :: 3.8
Classifier: Programming Language :: Python :: 3.9
Classifier: Programming Language :: Python :: 3.10
Classifier: Programming Language :: Python :: 3.11
Classifier: Programming Language :: Python :: 3.12
